mcp_server_garmincn/__init__.py
mcp_server_garmincn/__main__.py
mcp_server_garmincn/service/garmincn_service.py
mcp_server_garmincn/tools/garmin_health.py
mcp_server_garmincn-0.1.0.dist-info/METADATA
mcp_server_garmincn-0.1.0.dist-info/WHEEL
mcp_server_garmincn-0.1.0.dist-info/entry_points.txt
mcp_server_garmincn-0.1.0.dist-info/top_level.txt
mcp_server_garmincn-0.1.0.dist-info/RECORD
