Metadata-Version: 2.4
Name: mcp-server-garmincn
Version: 0.1.0
Summary: 用于大模型的MCP服务，提供获取用户的佳明数据的tool
Requires-Python: >=3.13
Requires-Dist: fastmcp>=2.4.0
Requires-Dist: garminconnect>=0.2.26
